{"error": 448, "message": "OK", "parameters": {"id": 7656, "name": "Coupon Code Guide", "created_at": "2023-03-18 03:01:42.23006", "updated_at": "2023-03-29 19:26:50.144933", "wikipedia": null, "keywords": null, "related": null, "slug": "coupon-code-guide", "is_comprehensively_reviewed": false, "rating": 32, "status": null, "image": "https://s3.tosdr.org/logos/7656.png", "url": "couponcodeguide.com", "documents": [{"id": 14747, "name": "Terms & Conditions, Privacy Policy", "url": "https://www.couponcodeguide.com/en/info/terms-and-privacy", "xpath": "//body", "text": null, "created_at": "2023-03-18 03:01:42.261643", "updated_at": "2023-03-18 03:02:19.004394"}], "points": [], "urls": ["couponcodeguide.com"]}}