{"error": 448, "message": "OK", "parameters": {"id": 8836, "name": "Lifeline ", "created_at": "2023-07-06 22:50:17.6617", "updated_at": "2023-07-07 10:02:13.56802", "wikipedia": null, "keywords": null, "related": null, "slug": "lifeline", "is_comprehensively_reviewed": false, "rating": 32, "status": null, "image": "https://s3.tosdr.org/logos/8836.png", "url": "lifeline.com", "documents": [{"id": 17266, "name": "Terms of Use ", "url": "https://www.lifeline.com/terms-of-use/ ", "xpath": "", "text": null, "created_at": "2023-07-06 22:50:17.721951", "updated_at": "2023-07-06 22:50:17.721951"}, {"id": 17265, "name": "Privacy Policy ", "url": "https://www.lifeline.com/privacy-policy/", "xpath": "//body", "text": null, "created_at": "2023-07-06 22:50:17.691148", "updated_at": "2023-07-06 22:50:23.377306"}], "points": [], "urls": ["lifeline.com"]}}