{"error": 448, "message": "OK", "parameters": {"id": 9865, "name": "MegaUp", "created_at": "2023-11-15 18:59:14.74131", "updated_at": "2023-11-15 23:03:15.379005", "wikipedia": null, "keywords": null, "related": null, "slug": "megaup", "is_comprehensively_reviewed": false, "rating": 32, "status": null, "image": "https://s3.tosdr.org/logos/9865.png", "url": "megaup.net", "documents": [{"id": 19653, "name": "Terms and Conditions", "url": "https://megaup.net/terms.html", "xpath": "//body", "text": null, "created_at": "2023-11-15 18:59:14.775561", "updated_at": "2023-11-15 18:59:21.68423"}], "points": [], "urls": ["megaup.net"]}}