{"error": 448, "message": "OK", "parameters": {"id": 9328, "name": "Edmunds", "created_at": "2023-08-20 03:07:53.32992", "updated_at": "2023-08-20 10:02:15.957562", "wikipedia": "https://en.wikipedia.org/wiki/Edmunds_(company)", "keywords": null, "related": null, "slug": "edmunds", "is_comprehensively_reviewed": false, "rating": 32, "status": null, "image": "https://s3.tosdr.org/logos/9328.png", "url": "edmunds.com", "documents": [{"id": 18299, "name": "Privacy Statement", "url": "https://www.edmunds.com/about/privacy.html", "xpath": "/html/body/div[1]/div/main/div[2]/div[1]/div", "text": null, "created_at": "2023-08-20 03:07:53.361237", "updated_at": "2023-08-20 03:08:13.388033"}, {"id": 18300, "name": "Visitor Agreement", "url": "https://www.edmunds.com/about/visitor-agreement.html", "xpath": "/html/body/div[1]/div/main/div[2]/div[1]/div/div", "text": null, "created_at": "2023-08-20 03:08:39.440544", "updated_at": "2023-08-20 03:08:39.440544"}, {"id": 18301, "name": "Copyright Notice", "url": "https://www.edmunds.com/copyright-trademark-notices/", "xpath": "/html/body/div[1]/div/div[2]/main/div[2]/div", "text": null, "created_at": "2023-08-20 03:09:31.69338", "updated_at": "2023-08-20 03:09:31.69338"}], "points": [], "urls": ["edmunds.com"]}}